{
  "id": "2518094",
  "name": "许天佑",
  "font_family": "iconfont",
  "css_prefix_text": "icon-",
  "description": "",
  "glyphs": [
    {
      "icon_id": "7549831",
      "name": "删除",
      "font_class": "delete",
      "unicode": "e6a9",
      "unicode_decimal": 59049
    },
    {
      "icon_id": "11372640",
      "name": "编辑",
      "font_class": "edit",
      "unicode": "e8ac",
      "unicode_decimal": 59564
    },
    {
      "icon_id": "15838441",
      "name": "chart-bar",
      "font_class": "chart",
      "unicode": "e667",
      "unicode_decimal": 58983
    },
    {
      "icon_id": "11474220",
      "name": "bussiness-man",
      "font_class": "resume",
      "unicode": "e6ef",
      "unicode_decimal": 59119
    },
    {
      "icon_id": "11488118",
      "name": "save",
      "font_class": "save",
      "unicode": "e762",
      "unicode_decimal": 59234
    },
    {
      "icon_id": "11488171",
      "name": "tool-hardware",
      "font_class": "tool",
      "unicode": "e76e",
      "unicode_decimal": 59246
    },
    {
      "icon_id": "11488256",
      "name": "folder-fill",
      "font_class": "file",
      "unicode": "e77f",
      "unicode_decimal": 59263
    },
    {
      "icon_id": "13087822",
      "name": "仓库",
      "font_class": "warehouse",
      "unicode": "e7c1",
      "unicode_decimal": 59329
    },
    {
      "icon_id": "18267910",
      "name": "查验",
      "font_class": "chayan",
      "unicode": "e98e",
      "unicode_decimal": 59790
    },
    {
      "icon_id": "18267931",
      "name": "链接",
      "font_class": "lianjie",
      "unicode": "e992",
      "unicode_decimal": 59794
    },
    {
      "icon_id": "18267937",
      "name": "管理",
      "font_class": "guanli",
      "unicode": "e993",
      "unicode_decimal": 59795
    },
    {
      "icon_id": "18267953",
      "name": "数字化",
      "font_class": "shuzihua",
      "unicode": "e99a",
      "unicode_decimal": 59802
    },
    {
      "icon_id": "18267958",
      "name": "数据库",
      "font_class": "shujuku",
      "unicode": "e99b",
      "unicode_decimal": 59803
    },
    {
      "icon_id": "18267974",
      "name": "文档",
      "font_class": "word",
      "unicode": "e99c",
      "unicode_decimal": 59804
    },
    {
      "icon_id": "8777224",
      "name": "copy",
      "font_class": "copy",
      "unicode": "e64c",
      "unicode_decimal": 58956
    }
  ]
}
